aury/ai/model/__init__.py
aury/ai/model/_version.py
aury/ai/model/client.py
aury/ai/model/context.py
aury/ai/model/errors.py
aury/ai/model/instrumentation.py
aury/ai/model/retry.py
aury/ai/model/structured.py
aury/ai/model/tools.py
aury/ai/model/types.py
aury/ai/model/providers/base.py
aury/ai/model/providers/doubao.py
aury/ai/model/providers/openai.py
aury/ai/model/providers/openrouter.py
aury/ai/model/providers/registry.py
aury_ai_model-0.0.16.dist-info/METADATA
aury_ai_model-0.0.16.dist-info/WHEEL
aury_ai_model-0.0.16.dist-info/RECORD
