Metadata-Version: 2.4
Name: aury-ai-model
Version: 0.0.16
Summary: Add your description here
Requires-Python: >=3.12
Requires-Dist: json-repair>=0.54.3
Requires-Dist: openai>=2.12.0
Requires-Dist: pydantic>=2.12.5
Requires-Dist: tenacity>=9.1.2
Provides-Extra: all
Requires-Dist: volcengine-python-sdk[ark]>=1.0; extra == 'all'
Provides-Extra: doubao
Requires-Dist: volcengine-python-sdk[ark]>=1.0; extra == 'doubao'
